gitea_backup/__init__.py
gitea_backup/gitea_backup.py
gitea_backup-2.1.3.data/scripts/gitea-backup
gitea_backup-2.1.3.dist-info/LICENSE.txt
gitea_backup-2.1.3.dist-info/METADATA
gitea_backup-2.1.3.dist-info/WHEEL
gitea_backup-2.1.3.dist-info/top_level.txt
gitea_backup-2.1.3.dist-info/zip-safe
gitea_backup-2.1.3.dist-info/RECORD
