Metadata-Version: 2.1
Name: gitea-backup
Version: 2.1.3
Summary: backup a gitea user or organization
Home-page: http://github.com/simplebackups/python-gitea-backup
Author: simplebackups
Author-email: simplebackups.io@gmail.com
License: MIT
Classifier: Development Status :: 5 - Production/Stable
Classifier: Topic :: System :: Archiving :: Backup
Classifier: License :: OSI Approved :: MIT License
Classifier: Programming Language :: Python :: 3.5
Classifier: Programming Language :: Python :: 3.6
Classifier: Programming Language :: Python :: 3.7
Classifier: Programming Language :: Python :: 3.8
License-File: LICENSE.txt
